rtd_flinx_shim.py
rtd_flinx_shim-0.1.3.dist-info/entry_points.txt
rtd_flinx_shim-0.1.3.dist-info/LICENSE
rtd_flinx_shim-0.1.3.dist-info/WHEEL
rtd_flinx_shim-0.1.3.dist-info/METADATA
rtd_flinx_shim-0.1.3.dist-info/RECORD
