Metadata-Version: 2.1
Name: rtd-flinx-shim
Version: 0.1.3
Summary: Trick Read the Docs into running Flinx.
Home-page: https://github.com/osteele/rtd-flinx-shim
License: UNKOWN
Author: Oliver Steele
Author-email: steele@osteele.com
Requires-Python: >=3.0
Classifier: Programming Language :: Python :: 3
Classifier: Programming Language :: Python :: 3.4
Classifier: Programming Language :: Python :: 3.5
Classifier: Programming Language :: Python :: 3.6
Classifier: Programming Language :: Python :: 3.7
Classifier: Topic :: Software Development :: Build Tools
Classifier: Topic :: Software Development :: Libraries :: Python Modules
Requires-Dist: flinx (>=0.1.1,<0.2.0)
